{
  "title": "알바 텃세 어떻게 하지",
  "content": "첫 알반데 뷔페알바 하고있거든 근데 여기사람들 중간중간 비는 시간마다 자기들끼리만 놀고 난 안끼워주는데 이것도 텃세 맞지..? 일도 내가 직접 물어봐야 알려주고 안 물어보면 그냥 뻘쭘하게가만히 있게 둬 일하러 온거니까 그냥 일만 해도 괜찮은데 문제는 뭐 해야할지 모르겠는 애매한 대기시긴때 너무 뻘쭘해 나쁜사람들까진 아닌데 신입한테 그냥 신경끄는 느낌이야 뻘쭘할때 폰도 못해 시시티비로 보고있어서..",
  "author": "ㅇㅇ",
  "date": "2025.01.09 11:07",
  "views": 6,
  "likes": 1,
  "comments": [
    {
      "author": "베플",
      "content": "애기야~~ 이게 무슨 텃새냐~? 니가 적극적으로 끼고 붙임성있게 굴어야지. 그 사람들이 뭐가 아쉬워서 너를 먼저 챙기겠니? 세상 많이 배워라~~",
      "date": "2025.01.10 17:41",
      "likes": 0,
      "dislikes": 0
    },
    {
      "author": "베플",
      "content": "이게뭔텃세임..? 당연히첨엔 어쩔수없는거지;; 넌 학창시절에 겉도는애들 놀때마다 끼워주고 햇냐",
      "date": "2025.01.10 17:09",
      "likes": 0,
      "dislikes": 0
    }
  ]
}